iconclass/__init__.py
iconclass/data.zip
iconclass-0.29.dist-info/LICENSE
iconclass-0.29.dist-info/METADATA
iconclass-0.29.dist-info/WHEEL
iconclass-0.29.dist-info/RECORD
