Metadata-Version: 2.3
Name: iconclass
Version: 0.29
Summary: This package provides a Python interface to using ICONCLASS.
License: MIT
Author: Etienne Posthumus
Author-email: ep@epoz.org
Requires-Python: >=3.7,<4.0
Classifier: License :: OSI Approved :: MIT License
Classifier: Programming Language :: Python :: 3
Classifier: Programming Language :: Python :: 3.7
Classifier: Programming Language :: Python :: 3.8
Classifier: Programming Language :: Python :: 3.9
Classifier: Programming Language :: Python :: 3.10
Classifier: Programming Language :: Python :: 3.11
Classifier: Programming Language :: Python :: 3.12
Classifier: Programming Language :: Python :: 3.13
Project-URL: Homepage, https://iconclass.org/
